.gitignore
.pre-commit-config.yaml
AUTHORS
CHANGELOG.md
LICENSE
MANIFEST.in
README.rst
pyproject.toml
pytest.ini
setup.cfg
setup.py
.github/workflows/flake8.yml
.github/workflows/publish.yml
.github/workflows/test.yml
topobank_publication/__init__.py
topobank_publication/apps.py
topobank_publication/forms.py
topobank_publication/models.py
topobank_publication/serializers.py
topobank_publication/signals.py
topobank_publication/urls.py
topobank_publication/utils.py
topobank_publication/views.py
topobank_publication.egg-info/PKG-INFO
topobank_publication.egg-info/SOURCES.txt
topobank_publication.egg-info/dependency_links.txt
topobank_publication.egg-info/entry_points.txt
topobank_publication.egg-info/requires.txt
topobank_publication.egg-info/top_level.txt
topobank_publication/management/__init__.py
topobank_publication/management/commands/__init__.py
topobank_publication/management/commands/complete_dois.py
topobank_publication/management/commands/renew_containers.py
topobank_publication/migrations/0001_initial.py
topobank_publication/migrations/0002_publication_authors.py
topobank_publication/migrations/0003_publication_publisher_orcid_id.py
topobank_publication/migrations/0004_auto_20210510_1252.py
topobank_publication/migrations/0005_publication_container.py
topobank_publication/migrations/0006_publication_authors_json.py
topobank_publication/migrations/0007_transfer_authors_names.py
topobank_publication/migrations/0008_remove_publication_authors.py
topobank_publication/migrations/0009_publication_doi_name.py
topobank_publication/migrations/0010_publication_doi_state.py
topobank_publication/migrations/0011_auto_20220228_1503.py
topobank_publication/migrations/0012_alter_publication_original_surface.py
topobank_publication/migrations/__init__.py
topobank_publication/static/licenses/cc0-1.0-legalcode.txt
topobank_publication/static/licenses/ccby-4.0-legalcode.txt
topobank_publication/static/licenses/ccbysa-4.0-legalcode.txt
topobank_publication/templates/license_radioselect.html
topobank_publication/templates/license_urls.html
topobank_publication/templates/multi_author_field.html
topobank_publication/templates/publication_error.html
topobank_publication/templates/publication_rate_too_high.html
