Metadata-Version: 2.1
Name: topobank-publication
Version: 1.6.2
Summary: This is a plugin for "topobank" for publishing digital surface twins (including assigning DOIs) via DataCite.
Author-email: Michael Röttger <info@michael-roettger.de>, Lars Pastewka <lars.pastewka@imtek.uni-freiburg.de>
License: MIT License
Project-URL: homepage, https://contact.engineering
Project-URL: repository, https://github.com/ContactEngineering/topobank-publication
Classifier: Development Status :: 5 - Production/Stable
Classifier: Environment :: Web Environment
Classifier: Framework :: Django
Classifier: Framework :: Django :: 3.2
Classifier: Framework :: Celery
Classifier: Intended Audience :: Developers
Classifier: License :: OSI Approved :: MIT License
Classifier: Operating System :: POSIX
Classifier: Programming Language :: Python
Classifier: Programming Language :: Python :: 3
Classifier: Programming Language :: Python :: 3 :: Only
Classifier: Programming Language :: Python :: 3.8
Classifier: Programming Language :: Python :: 3.9
Classifier: Topic :: Internet :: WWW/HTTP
Classifier: Topic :: Internet :: WWW/HTTP :: Dynamic Content
Requires-Python: >=3.8.0
License-File: LICENSE
License-File: AUTHORS
Requires-Dist: datacite
Requires-Dist: short_url
Requires-Dist: bleach>=3.3.0
Provides-Extra: dev
